{
  "meta": {
    "bookId": "CB_A0LAjlAkU4Dg6gS6giBo31pR",
    "title": "羊毛战记三部曲",
    "author": "[美]休·豪伊",
    "translator": "",
    "cover": "https://res.weread.qq.com/wrepub/CB_6CzGb7Gds4sq6gK6gw3sN7A9_parsecover",
    "coverDownloaded": true,
    "localCover": "data/未分类/羊毛战记三部曲_31pR/CB_A0LAjlAkU4Dg6gS6giBo31pR.jpg",
    "intro": "",
    "category": "",
    "publisher": "浦睿文化·湖南文艺出版社",
    "publishTime": "",
    "isbn": "",
    "wordCount": 0,
    "newRating": 0,
    "newRatingCount": 0,
    "newRatingDetail": {
      "good": 0,
      "fair": 0,
      "poor": 0,
      "recent": 0,
      "deepV": 0,
      "myRating": "",
      "title": "待评分"
    },
    "appLink": "weread://reading?bId=CB_A0LAjlAkU4Dg6gS6giBo31pR",
    "lastSync": "2026-05-23T17:59:57Z",
    "readingProgress": "2%",
    "readingTime": "0分钟",
    "finishedDate": "",
    "noteCount": 0,
    "reviewCount": 0,
    "bookmarkCount": 0
  },
  "chapters": [],
  "content": [],
  "bookReviews": [],
  "hotBookmarks": [],
  "readProgress": {
    "chapterUid": 5,
    "chapterOffset": 13861,
    "progress": 2,
    "updateTime": 1687443107,
    "recordReadingTime": 0,
    "finishTime": ""
  }
}