{
  "meta": {
    "bookId": "CB_ELk8gm8fx41L6st6t96X00mI",
    "title": "我的人生样样稀松照样赢_呆伯特_的逆袭人生_美_史考特亚当斯著_Z_Library",
    "author": "（美）史考特·亚当斯著",
    "translator": "",
    "cover": "https://res.weread.qq.com/wrepub/CB_7G3Ga7GZhCkM6kk6kk03P2NW_parsecover",
    "coverDownloaded": true,
    "localCover": "data/未分类/我的人生样样稀松照样赢_呆伯特_的逆袭人生_美_史考特亚当斯著_Z_Library_00mI/CB_ELk8gm8fx41L6st6t96X00mI.jpg",
    "intro": "",
    "category": "",
    "publisher": "",
    "publishTime": "",
    "isbn": "",
    "wordCount": 0,
    "newRating": 0,
    "newRatingCount": 0,
    "newRatingDetail": {
      "good": 0,
      "fair": 0,
      "poor": 0,
      "recent": 0,
      "deepV": 0,
      "myRating": "",
      "title": "待评分"
    },
    "appLink": "weread://reading?bId=CB_ELk8gm8fx41L6st6t96X00mI",
    "lastSync": "2026-05-21T09:28:41Z",
    "readingProgress": "9%",
    "readingTime": "0分钟",
    "finishedDate": "",
    "noteCount": 0,
    "reviewCount": 0,
    "bookmarkCount": 0
  },
  "chapters": [],
  "content": [],
  "bookReviews": [],
  "hotBookmarks": [],
  "readProgress": {
    "chapterUid": 3,
    "chapterOffset": 0,
    "progress": 9,
    "updateTime": 1736394747,
    "recordReadingTime": 0,
    "finishTime": ""
  }
}